Metadata-Version: 1.1
Name: gradesG1
Version: 0.0.1
Summary: semeter and overall GPA calculator
Home-page: UNKNOWN
Author: Abdulbari
Author-email: abdulbarazizkhan@gmail.com
License: MIT
Keywords: calculator
Platform: UNKNOWN
Classifier: Development Status :: 5 - Production/Stable
Classifier: Intended Audience :: Education
Classifier: Operating System :: Microsoft :: Windows :: Windows 10
Classifier: License :: OSI Approved :: MIT License
Classifier: Programming Language :: Python :: 3
